seven_segment_decoder.sv
// Common cathode mode

module seven_segment_decoder (
    input  logic [3:0] num,  // 4-bit input (0–9)
    output logic [6:0] seg   // 7-bit output (gfedcba)
);

    always_comb begin
        case (num)
            4'd0 : seg = 7'b0111111; // 0
            4'd1 : seg = 7'b0000110; // 1
            4'd2 : seg = 7'b1011011; // 2
            4'd3 : seg = 7'b1001111; // 3
            4'd4 : seg = 7'b1100110; // 4
            4'd5 : seg = 7'b1101101; // 5
            4'd6 : seg = 7'b1111101; // 6
            4'd7 : seg = 7'b0000111; // 7
            4'd8 : seg = 7'b1111111; // 8
            4'd9 : seg = 7'b1101111; // 9
            default: seg = 7'b1000000; // Invalid input (usually displays '-')
        endcase
    end

endmodule

seven_segment_decoder_tb.sv
module seven_segment_decoder_tb;
    timeunit 1ns;
    timeprecision 1ps;
    
    logic [3:0] num;
    logic [6:0] seg;
    
    seven_segment_decoder dut(.*);
    
    initial begin
        $dumpfile("dump.vcd");
        $dumpvars(0, dut);
        
        // Test each digit from 0 to 9
        num <= 4'd0;
        #10 assert (seg == 7'b0111111) else $error("Fail: Digit 0");
        
        #10 num <= 4'd1;
        #10 assert (seg == 7'b0000110) else $error("Fail: Digit 1");
        
        #10 num <= 4'd2;
        #10 assert (seg == 7'b1011011) else $error("Fail: Digit 2");
        
        #10 num <= 4'd3;
        #10 assert (seg == 7'b1001111) else $error("Fail: Digit 3");
        
        #10 num <= 4'd4;
        #10 assert (seg == 7'b1100110) else $error("Fail: Digit 4");
        
        #10 num <= 4'd5;
        #10 assert (seg == 7'b1101101) else $error("Fail: Digit 5");
        
        #10 num <= 4'd6;
        #10 assert (seg == 7'b1111101) else $error("Fail: Digit 6");
        
        #10 num <= 4'd7;
        #10 assert (seg == 7'b0000111) else $error("Fail: Digit 7");
        
        #10 num <= 4'd8;
        #10 assert (seg == 7'b1111111) else $error("Fail: Digit 8");
        
        #10 num <= 4'd9;
        #10 assert (seg == 7'b1101111) else $error("Fail: Digit 9");
        
        // Test invalid input
        #10 num <= 4'd10;
        #10 assert (seg == 7'b1000000) else $error("Fail: Invalid input");
        
        #10 $finish;
    end
endmodule

simulation/modelsim/dump.vcd
$date
	Sun Mar 09 19:57:52 2025
$end
$version
	ModelSim Version 2020.1
$end
$timescale
	1ps
$end

$scope module seven_segment_decoder_tb $end

$scope module dut $end
$var wire 1 ! num [3] $end
$var wire 1 " num [2] $end
$var wire 1 # num [1] $end
$var wire 1 $ num [0] $end
$var reg 7 % seg [6:0] $end
$upscope $end
$upscope $end
$enddefinitions $end
#0
$dumpvars
b111111 %
0$
0#
0"
0!
$end
#20000
1$
b110 %
#40000
0$
1#
b1011011 %
#60000
1$
b1001111 %
#80000
0$
0#
1"
b1100110 %
#100000
1$
b1101101 %
#120000
0$
1#
b1111101 %
#140000
1$
b111 %
#160000
0$
0#
0"
1!
b1111111 %
#180000
1$
b1101111 %
#200000
0$
1#
b1000000 %
